faketranslate/__init__.py
faketranslate/metadata.py
faketranslate/setting.py
faketranslate/translate.py
fake_translate-0.1.3.dist-info/LICENSE
fake_translate-0.1.3.dist-info/METADATA
fake_translate-0.1.3.dist-info/WHEEL
fake_translate-0.1.3.dist-info/top_level.txt
fake_translate-0.1.3.dist-info/RECORD
