Metadata-Version: 2.1
Name: fake-translate
Version: 0.1.3
Summary: An efficient and practical translation tool
Home-page: https://github.com/HeywoodKing/faketranslate
Author: hywell
Author-email: opencoding@hotmail.com
Maintainer: hywell
Maintainer-email: opencoding@hotmail.com
License: AGPLv3+
Download-URL: https://github.com/HeywoodKing/faketranslate
Project-URL: Documentation, https://packaging.python.org/tutorials/distributing-packages/
Project-URL: Funding, https://donate.pypi.org
Project-URL: Source, https://github.com/pypa/sampleproject/
Project-URL: Tracker, https://github.com/pypa/sampleproject/issues
Keywords: python translate
Platform: all
Classifier: Development Status :: 2 - Pre-Alpha
Classifier: Environment :: Web Environment
Classifier: Environment :: Console
Classifier: Intended Audience :: Developers
Classifier: License :: OSI Approved :: GNU Affero General Public License v3 or later (AGPLv3+)
Classifier: Natural Language :: Chinese (Simplified)
Classifier: Operating System :: OS Independent
Classifier: Programming Language :: Python :: 2
Classifier: Programming Language :: Python :: 3
Classifier: Topic :: Utilities
Requires-Python: >=2.6
Requires-Dist: requests (>=2.22.0)
Requires-Dist: fake-useragent (>=0.1.11)
